{"TotalTicks":377,"Players":[{"Placement":1,"Seed":16952,"Score":31,"Id":"7b2ea15d-1aa1-46fa-87fa-d9c82f3b9058","Nickname":"Jup Bot","MatchPoints":8},{"Placement":3,"Seed":26273,"Score":31,"Id":"f4e02796-d0b7-49ee-9448-83ecf5ec010e","Nickname":"PlayerNumber","MatchPoints":4},{"Placement":4,"Seed":23391,"Score":12,"Id":"6cfa1192-f641-47fb-abaf-664a991e0c73","Nickname":"ReferenceBot","MatchPoints":2},{"Placement":2,"Seed":8758,"Score":40,"Id":"8c834b70-c07f-4efe-a020-f1ebb70ddd09","Nickname":"Player#One","MatchPoints":6}],"WorldSeeds":[36679],"WinningBot":{"Id":"7b2ea15d-1aa1-46fa-87fa-d9c82f3b9058","Size":49,"Speed":5,"GameObjectType":1,"CurrentHeading":261,"Position":{"X":-224,"Y":425}}}